Workbook
Name Slicer_Amount: #N/A
Name Slicer_GST: #N/A
Name Slicer_GST_Amount: #N/A
Name Slicer_Product_Name: #N/A
Name Slicer_Rate: #N/A
Name Slicer_Total_Amount: #N/A

Sheet formula
F1: VLOOK UP
A2: PRODUCT NAME | C2: =VLOOKUP('product master'!B2,'product master'!B1:D7,1,FALSE) -> laptop
A3: RATE | B3: =VLOOKUP('product master'!B2,'product master'!B2:D7,2,FALSE) -> 60000
A4: GST | B4: =VLOOKUP('product master'!B2,'product master'!B2:D7,3,FALSE) -> 18
E7: hlook up
A8: PRODUCT NAME | C8: =HLOOKUP('product master'!B2,'product master'!B2:D7,2,FALSE) -> mouse
A9: RATE | C9: 800
A10: GST | C10: 18
G11: index match
A13: laptop 7 | B13: =INDEX('Invoice Billing'!$H$2:$H$151,MATCH('Invoice Billing'!E2,'Invoice Billing'!$E$2:$E$151,0)) -> 120000

Sheet CONCLUSION

Sheet pivot table
A1: Row Labels | B1: Sum of Quantity
A2: Formula1 | H2: Row Labels | I2: Sum of GST Amount | K2: Row Labels | L2: Sum of Total Amount
A3: Grand Total | H3: Laptop | I3: 2766204 | K3: Laptop | L3: 6254004
H4: Keyboard | I4: 311733 | K4: Keyboard | L4: 1746583
E5: Row Labels | F5: Sum of Rate | H5: Mobile | I5: 1401156 | K5: Mobile | L5: 2255356
E6: Laptop | F6: 507800 | H6: Monitor | I6: 1010610 | K6: Monitor | L6: 6625110
E7: Keyboard | F7: 146030 | H7: Mouse | I7: 85527 | K7: Mouse | L7: 362677
E8: Mobile | F8: 127800 | H8: Printer | I8: 305569.8 | K8: Printer | L8: 1112179.8
E9: Monitor | F9: 297500 | H9: Formula1 | K9: Formula1
E10: Mouse | F10: 57350 | H10: Grand Total | I10: 5880799.8 | K10: Grand Total | L10: 18355910
E11: Printer | F11: 140430
E12: Formula1
E13: Grand Total | F13: 1276910 | I13: Row Labels | J13: Sum of GST %
I14: Laptop | J14: 450
I15: Keyboard | J15: 450
I16: Mobile | J16: 450
I17: Monitor | J17: 450
I18: Mouse | J18: 450
I19: Printer | J19: 450
I20: Formula1
I21: Grand Total | J21: 2700

Sheet dashboard

Sheet Invoice Billing
A1: Invoice No | B1: Date | C1: Customer Name | D1: Mobile No | E1: Product Name | F1: Quantity | G1: Rate | H1: Amount | I1: GST % | J1: GST Amount | K1: Total Amount | L1: Payment Status
A2: INV-0001 | B2: 46023 | C2: Arun Traders | D2: 9876510001 | E2: laptop | F2: 2 | G2: 60000 | H2: =F2*G2 -> 120000 | I2: 18 | J2: =H2*I2 -> 2160000 | K2: =H2+J2 -> 2280000 | L2: Paid
A3: INV-0002 | B3: 46024 | C3: Kumar Traders | D3: 9876510002 | E3: Mobile | F3: 7 | G3: 10000 | H3: =F3*G3 -> 70000 | I3: 18 | J3: =H3*I3 -> 1260000 | K3: =H3+J3 -> 1330000 | L3: Paid
A4: INV-0003 | B4: 46025 | C4: Priya Traders | D4: 9876510003 | E4: Printer | F4: 9 | G4: 1000 | H4: =F4*G4 -> 9000 | I4: 18 | J4: =H4*I4 -> 162000 | K4: =H4+J4 -> 171000 | L4: Paid
A5: INV-0004 | B5: 46026 | C5: Ravi Traders | D5: 9876510004 | E5: Keyboard | F5: 3 | G5: 1000 | H5: =F5*G5 -> 3000 | I5: 18 | J5: =H5*I5 -> 54000 | K5: =H5+J5 -> 57000 | L5: Paid
A6: INV-0005 | B6: 46027 | C6: Suresh Traders | D6: 9876510005 | E6: Mouse | F6: 2 | G6: 1000 | H6: =F6*G6 -> 2000 | I6: 18 | J6: =H6*I6 -> 36000 | K6: =H6+J6 -> 38000 | L6: Paid
A7: INV-0006 | B7: 46028 | C7: Anitha Traders | D7: 9876510006 | E7: Monitor | F7: 1 | G7: 1000 | H7: =F7*G7 -> 1000 | I7: 18 | J7: =H7*I7/100 -> 180 | K7: =H7+J7 -> 1180 | L7: Paid
A8: INV-0007 | B8: 46029 | C8: Arun Traders | D8: 9876510007 | E8: Laptop | F8: 7 | G8: 60000 | H8: =F8*G8 -> 420000 | I8: 18 | J8: =H8*I8/100 -> 75600 | K8: =H8+J8 -> 495600 | L8: Paid
A9: INV-0008 | B9: 46030 | C9: Kumar Traders | D9: 9876510008 | E9: Mobile | F9: 20 | G9: 10000 | H9: =F9*G9 -> 200000 | I9: 18 | J9: =H9*I9/100 -> 36000 | K9: =H9+J9 -> 236000 | L9: Paid
A10: INV-0009 | B10: 46031 | C10: Priya Traders | D10: 9876510009 | E10: Printer | F10: 11 | G10: 1000 | H10: =F10*G10 -> 11000 | I10: 18 | J10: =H10*I10/100 -> 1980 | K10: =H10+J10 -> 12980 | L10: Paid
A11: INV-0010 | B11: 46032 | C11: Ravi Traders | D11: 9876510010 | E11: Keyboard | F11: 12 | G11: 1000 | H11: =F11*G11 -> 12000 | I11: 18 | J11: =H11*I11/100 -> 2160 | K11: =H11+J11 -> 14160 | L11: Paid
A12: INV-0011 | B12: 46033 | C12: Suresh Traders | D12: 9876510011 | E12: Mouse | F12: 13 | G12: 1000 | H12: =F12*G12 -> 13000 | I12: 18 | J12: =H12*I12/100 -> 2340 | K12: =H12+J12 -> 15340 | L12: Paid
A13: INV-0012 | B13: 46034 | C13: Anitha Traders | D13: 9876510012 | E13: Monitor | F13: 25 | G13: 1000 | H13: =F13*G13 -> 25000 | I13: 18 | J13: =H13*I13/100 -> 4500 | K13: =H13+J13 -> 29500 | L13: Paid
A14: INV-0013 | B14: 46035 | C14: Arun Traders | D14: 9876510013 | E14: Laptop | F14: 32 | G14: 60000 | H14: =F14*G14 -> 1920000 | I14: 18 | J14: =H14*I14/100 -> 345600 | K14: =H14+J14 -> 2265600 | L14: Paid
A15: INV-0014 | B15: 46036 | C15: Kumar Traders | D15: 9876510014 | E15: Mobile | F15: 10 | G15: 23000 | H15: =F15*G15 -> 230000 | I15: 18 | J15: =H15*I15/100 -> 41400 | K15: =H15+J15 -> 271400 | L15: Paid
A16: INV-0015 | B16: 46037 | C16: Priya Traders | D16: 9876510015 | E16: Printer | F16: 7 | G16: 1000 | H16: =F16*G16 -> 7000 | I16: 18 | J16: =H16*I16/100 -> 1260 | K16: =H16+J16 -> 8260 | L16: Paid
A17: INV-0016 | B17: 46038 | C17: Ravi Traders | D17: 9876510016 | E17: Keyboard | F17: 22 | G17: 1000 | H17: =F17*G17 -> 22000 | I17: 18 | J17: =H17*I17/100 -> 3960 | K17: =H17+J17 -> 25960 | L17: Paid
A18: INV-0017 | B18: 46039 | C18: Suresh Traders | D18: 9876510017 | E18: Mouse | F18: 2 | G18: 1000 | H18: =F18*G18 -> 2000 | I18: 18 | J18: =H18*I18/100 -> 360 | K18: =H18+J18 -> 2360 | L18: Paid
... A151: INV-0150 | B151: 46172 | C151: Anitha Traders | D151: 9876510150 | E151: Monitor | F151: 2 | G151: 5000 | H151: =F151*G151 -> 10000 | I151: 18 | J151: =H151*I151/100 -> 1800 | K151: =H151+J151 -> 11800 | L151: Paid

Sheet CUSTOMER MASTER
A1: CUSTOMER ID | B1: CUSTOMER NAME | C1: MOBILE NO
A2: C001 | B2: ARUN TRADERS | C2: 9876510001
A3: C002 | B3: KUMAR TRADERS | C3: 9876510002
A4: C003 | B4: PRIYA TRADERS | C4: 9876510003
A5: C004 | B5: RAVI TRADERS | C5: 9876510004
A6: C005 | B6: SURESH TRADERS | C6: 9876510005
A7: C006 | B7: ANITHA TRADERS | C7: 9876510006

Sheet SALES SUMMARY
A1: DESCRIBE | B1: VALUE
A2: TOTAL SALES | B2: =SUM('Invoice Billing'!K2:K151) -> 18355910
A3: AVERAGE SALES | B3: =AVERAGE('Invoice Billing'!K2:K151) -> 122372.73
A4: HSMAX | B4: =MAX('Invoice Billing'!K2:K151) -> 5451600
A5: LS MIN | B5: =MIN('Invoice Billing'!K2:K151) -> 413
A6: COUNT | B6: =COUNT('Invoice Billing'!K2:K151) -> 150
A7: TOTAL QTY | B7: =SUM('Invoice Billing'!F2:F151) -> 698

Sheet product master
A1: PRODUCT ID | B1: PRODUCT NAME | C1: RATE | D1: GST
A2: 1 | B2: laptop | C2: 60000 | D2: 18
A3: 2 | B3: mouse | C3: 800 | D3: 18
A4: 3 | B4: keyboard | C4: 1200 | D4: 18
A5: 4 | B5: printer | C5: 5000 | D5: 18
A6: 5 | B6: mobile | C6: 10000 | D6: 18
A7: 6 | B7: monitor | C7: 8000 | D7: 18
